{"name":"sdk:pre-test","entryType":"measure","startTime":4264.4033,"duration":20.016599999999926,"detail":null,"success":true,"failure":"undefined","worker":"24480-0","methodName":"onPrepare"},{"name":"sdk:testhub:start","entryType":"measure","startTime":4267.0721,"duration":16.453700000000026,"detail":null,"success":true,"failure":"undefined","worker":"24480-0"},{"name":"sdk:setup","entryType":"measure","startTime":4288.1754,"duration":0.07120000000031723,"detail":null,"success":true,"failure":"undefined","worker":"24480-0","methodName":"onWorkerStart"},